nonebot_plugin_mcsmanager-0.1.0.dist-info/METADATA
nonebot_plugin_mcsmanager-0.1.0.dist-info/WHEEL
nonebot_plugin_mcsmanager-0.1.0.dist-info/licenses/LICENSE
nonebot_plugin_mcsmanager/__init__.py
nonebot_plugin_mcsmanager/api_models/instance.py
nonebot_plugin_mcsmanager/api_models/instance_outputlog.py
nonebot_plugin_mcsmanager/api_models/instances.py
nonebot_plugin_mcsmanager/api_models/overview.py
nonebot_plugin_mcsmanager/api_models/user.py
nonebot_plugin_mcsmanager/api_models/userlist.py
nonebot_plugin_mcsmanager/data_source.py
nonebot_plugin_mcsmanager/database_models.py
nonebot_plugin_mcsmanager/mcsm_api.py
nonebot_plugin_mcsmanager/models.py
nonebot_plugin_mcsmanager/templates/server_list.md.jinja
nonebot_plugin_mcsmanager/utils.py
nonebot_plugin_mcsmanager-0.1.0.dist-info/RECORD
