Metadata-Version: 2.1
Name: nonebot-plugin-mcsmanager
Version: 0.1.0
Summary: mcsm for nonebot2
Author-Email: kexue <x@kexue-cloud.cn>
License: MIT
Requires-Python: >=3.9
Requires-Dist: pydantic>=2.7.4
Requires-Dist: httpx>=0.27.0
Requires-Dist: nonebot-plugin-alconna>=0.47.0
Requires-Dist: nonebot-plugin-tortoise-orm>=0.1.2
